README.md
setup.py
axclf/__init__.py
axclf/_version.py
axclf.egg-info/PKG-INFO
axclf.egg-info/SOURCES.txt
axclf.egg-info/dependency_links.txt
axclf.egg-info/top_level.txt