Metadata-Version: 2.1
Name: axclf
Version: 0.2.0
Summary: save/restore plot limits
Home-page: http://github.com/serwy/axclf
Author: Roger D. Serwy
Author-email: roger.serwy@gmail.com
License: BSD License
Keywords: matplotlib
Platform: Windows
Platform: Linux
Platform: Solaris
Platform: Mac OS-X
Platform: Unix
Classifier: Development Status :: 4 - Beta
Classifier: Intended Audience :: Developers
Classifier: Intended Audience :: Science/Research
Classifier: License :: OSI Approved :: BSD License
